pillowfight/__init__.py
pillowfight/_clib.cp36-win_amd64.pyd
pypillowfight-0.2.2.dist-info/DESCRIPTION.rst
pypillowfight-0.2.2.dist-info/METADATA
pypillowfight-0.2.2.dist-info/RECORD
pypillowfight-0.2.2.dist-info/WHEEL
pypillowfight-0.2.2.dist-info/metadata.json
pypillowfight-0.2.2.dist-info/top_level.txt
