Metadata-Version: 2.0
Name: pypillowfight
Version: 0.2.2
Summary: Library containing various image processing algorithms
Home-page: https://github.com/openpaperwork/libpillowfight#readme
Author: Jerome Flesch
Author-email: jflesch@gmail.com
License: GPLv2
Download-URL: https://github.com/openpaperwork/libpillowfight/archive/0.2.2.zip
Keywords: image processing algorithm pillow pil
Platform: UNKNOWN
Classifier: Intended Audience :: Developers
Classifier: License :: OSI Approved :: GNU General Public License v3 or later (GPLv3+)
Classifier: Operating System :: POSIX :: Linux
Classifier: Programming Language :: Python
Classifier: Programming Language :: Python :: 3
Classifier: Programming Language :: Python :: 3.5
Classifier: Topic :: Multimedia :: Graphics :: Graphics Conversion
Requires-Dist: Pillow
